{
  "books": [
    {
      "id": "9WB1XDZ",
      "name": "Luculia intermedia Hutch.",
      "des": "magna bibendum imperdiet nullam orci pede venenatis non sodales sed tincidunt eu felis fusce posuere felis sed",
      "img": "https://picsum.photos/200/300?grayscale"
    },
    {
      "id": "0YH131Z",
      "name": "Begonia reniformis Dryand.",
      "des": "leo rhoncus sed vestibulum sit amet cursus id turpis integer aliquet massa id lobortis convallis",
      "img": "https://picsum.photos/200/300?grayscale"
    },
    {
      "id": "0DNE8ZZ",
      "name": "Furcraea foetida (L.) Haw.",
      "des": "fusce posuere felis sed lacus morbi sem mauris laoreet ut rhoncus aliquet pulvinar sed nisl nunc rhoncus dui vel",
      "img": "https://picsum.photos/200/300?grayscale"
    },
    {
      "id": "0K9G4ZX",
      "name": "Phaeophyscia insignis (Mereschk.) Moberg",
      "des": "hac habitasse platea dictumst maecenas ut massa quis augue luctus tincidunt nulla mollis molestie lorem quisque ut erat curabitur",
      "img": "https://picsum.photos/200/300?grayscale"
    },
    {
      "id": "0P503ZZ",
      "name": "Euphorbia discoidalis Chapm.",
      "des": "ultrices posuere cubilia curae duis faucibus accumsan odio curabitur convallis duis consequat dui nec",
      "img": "https://picsum.photos/200/300?grayscale"
    },
    {
      "id": "0BPT87Z",
      "name": "Cyperus pennatiformis Kük. var. pennatiformis",
      "des": "leo odio porttitor id consequat in consequat ut nulla sed",
      "img": "https://picsum.photos/200/300?grayscale"
    },
    {
      "id": "03HA3DZ",
      "name": "Adiantum vivesii Proctor",
      "des": "dolor morbi vel lectus in quam fringilla rhoncus mauris enim leo rhoncus sed vestibulum sit",
      "img": "https://picsum.photos/200/300?grayscale"
    },
    {
      "id": "047V35Z",
      "name": "Amphiachyris amoena (Shinners) Solbrig",
      "des": "ante nulla justo aliquam quis turpis eget elit sodales scelerisque mauris sit",
      "img": "https://picsum.photos/200/300?grayscale"
    },
    {
      "id": "01Q84ZZ",
      "name": "Cymopterus megacephalus M.E. Jones",
      "des": "vestibulum ante ipsum primis in faucibus orci luctus et ultrices posuere cubilia curae",
      "img": "https://picsum.photos/200/300?grayscale"
    },
    {
      "id": "0T160ZC",
      "name": "Crepis occidentalis Nutt. ssp. costata (A. Gray) Babc. & Stebbins",
      "des": "rutrum nulla nunc purus phasellus in felis donec semper sapien a libero nam",
      "img": "https://picsum.photos/200/300?grayscale"
    },
    {
      "id": "0F180Z3",
      "name": "Cochlearia L.",
      "des": "etiam pretium iaculis justo in hac habitasse platea dictumst etiam faucibus cursus urna ut",
      "img": "https://picsum.photos/200/300?grayscale"
    },
    {
      "id": "0RWX35Z",
      "name": "Lepanthopsis melanantha (Rchb. f.) Ames",
      "des": "molestie sed justo pellentesque viverra pede ac diam cras pellentesque volutpat dui maecenas",
      "img": "https://picsum.photos/200/300?grayscale"
    },
    {
      "id": "00160K4",
      "name": "Hieracium lachenalii C.C. Gmel.",
      "des": "porttitor id consequat in consequat ut nulla sed accumsan felis ut at dolor",
      "img": "https://picsum.photos/200/300?grayscale"
    },
    {
      "id": "BW38YZZ",
      "name": "Houstonia subviscosa (C. Wright ex A. Gray) A. Gray",
      "des": "eget congue eget semper rutrum nulla nunc purus phasellus in felis donec semper sapien a libero",
      "img": "https://picsum.photos/200/300?grayscale"
    },
    {
      "id": "0BP03KZ",
      "name": "Cladonia prolifica Ahti & S. Hammer",
      "des": "nullam varius nulla facilisi cras non velit nec nisi vulputate",
      "img": "https://picsum.photos/200/300?grayscale"
    },
    {
      "id": "B53MY0Z",
      "name": "Packera millefolium (Torr. & A. Gray) W.A. Weber & Á. Löve",
      "des": "vitae consectetuer eget rutrum at lorem integer tincidunt ante vel ipsum praesent",
      "img": "https://picsum.photos/200/300?grayscale"
    },
    {
      "id": "02B40ZZ",
      "name": "Diospyros kaki L. f.",
      "des": "suspendisse potenti cras in purus eu magna vulputate luctus cum sociis natoque penatibus et magnis dis parturient",
      "img": "https://picsum.photos/200/300?grayscale"
    },
    {
      "id": "0J073ZZ",
      "name": "Aciphylla ferox W.R.B. Oliv.",
      "des": "cubilia curae duis faucibus accumsan odio curabitur convallis duis consequat dui nec nisi volutpat eleifend donec ut dolor",
      "img": "https://picsum.photos/200/300?grayscale"
    },
    {
      "id": "0CR507Z",
      "name": "Beta trojana A. Pamukc. ex Aellen",
      "des": "integer ac neque duis bibendum morbi non quam nec dui luctus rutrum nulla tellus in sagittis dui vel nisl duis",
      "img": "https://picsum.photos/200/300?grayscale"
    },
    {
      "id": "009J0ZZ",
      "name": "Delonix Raf.",
      "des": "cras pellentesque volutpat dui maecenas tristique est et tempus semper est quam pharetra magna ac consequat metus",
      "img": "https://picsum.photos/200/300?grayscale"
    },
    {
      "id": "0YUS0JZ",
      "name": "Tabebuia rigida Urb.",
      "des": "mi integer ac neque duis bibendum morbi non quam nec dui luctus",
      "img": "https://picsum.photos/200/300?grayscale"
    },
    {
      "id": "00XM4ZQ",
      "name": "Zephyranthes proctorii Acev.-Rodr. & M.T. Strong",
      "des": "pede morbi porttitor lorem id ligula suspendisse ornare consequat lectus in est risus auctor sed tristique in tempus sit amet",
      "img": "https://picsum.photos/200/300?grayscale"
    },
    {
      "id": "B50MYZZ",
      "name": "Dendropemon purpureus (L.) Krug & Urb.",
      "des": "ante ipsum primis in faucibus orci luctus et ultrices posuere",
      "img": "https://picsum.photos/200/300?grayscale"
    },
    {
      "id": "04BH4ZX",
      "name": "Melinis minutiflora P. Beauv.",
      "des": "libero nam dui proin leo odio porttitor id consequat in consequat ut",
      "img": "https://picsum.photos/200/300?grayscale"
    },
    {
      "id": "0RCQ4ZZ",
      "name": "Helocarpon crassipes Th. Fr.",
      "des": "rhoncus aliquam lacus morbi quis tortor id nulla ultrices aliquet maecenas leo odio condimentum id luctus",
      "img": "https://picsum.photos/200/300?grayscale"
    },
    {
      "id": "041C49D",
      "name": "Deinandra corymbosa (DC.) B.G. Baldw.",
      "des": "amet nulla quisque arcu libero rutrum ac lobortis vel dapibus at diam nam",
      "img": "https://picsum.photos/200/300?grayscale"
    },
    {
      "id": "0FW",
      "name": "Cyrtandra crenata H. St. John & Storey",
      "des": "ullamcorper purus sit amet nulla quisque arcu libero rutrum ac",
      "img": "https://picsum.photos/200/300?grayscale"
    },
    {
      "id": "0NN83ZZ",
      "name": "Passiflora murucuja L.",
      "des": "maecenas pulvinar lobortis est phasellus sit amet erat nulla tempus vivamus in felis eu sapien",
      "img": "https://picsum.photos/200/300?grayscale"
    },
    {
      "id": "04H63DZ",
      "name": "Callitropsis nootkatensis (D. Don) Oerst. ex D.P. Little",
      "des": "magna ac consequat metus sapien ut nunc vestibulum ante ipsum primis in faucibus orci",
      "img": "https://picsum.photos/200/300?grayscale"
    },
    {
      "id": "0CWY00Z",
      "name": "Polypodium sibiricum Sipl.",
      "des": "ligula sit amet eleifend pede libero quis orci nullam molestie nibh in lectus",
      "img": "https://picsum.photos/200/300?grayscale"
    },
    {
      "id": "0QPNX4Z",
      "name": "Xylosma schwaneckeana (Krug & Urb.) Urb.",
      "des": "lorem integer tincidunt ante vel ipsum praesent blandit lacinia erat",
      "img": "https://picsum.photos/200/300?grayscale"
    },
    {
      "id": "0DWDX2Z",
      "name": "Ixophorus Schltdl.",
      "des": "quisque porta volutpat erat quisque erat eros viverra eget congue eget semper rutrum nulla nunc purus phasellus",
      "img": "https://picsum.photos/200/300?grayscale"
    },
    {
      "id": "04L34DZ",
      "name": "Astragalus canadensis L. var. canadensis",
      "des": "ultrices vel augue vestibulum ante ipsum primis in faucibus orci luctus et ultrices posuere cubilia curae",
      "img": "https://picsum.photos/200/300?grayscale"
    },
    {
      "id": "00SH4ZZ",
      "name": "Myriophyllum tenellum Bigelow",
      "des": "maecenas pulvinar lobortis est phasellus sit amet erat nulla tempus vivamus in felis eu sapien cursus vestibulum proin eu mi",
      "img": "https://picsum.photos/200/300?grayscale"
    },
    {
      "id": "0DVK0DZ",
      "name": "Helianthus debilis Nutt.",
      "des": "ut blandit non interdum in ante vestibulum ante ipsum primis in faucibus orci luctus et",
      "img": "https://picsum.photos/200/300?grayscale"
    },
    {
      "id": "0MB24ZZ",
      "name": "Gilia capitata Sims ssp. pedemontana V.E. Grant",
      "des": "nulla ac enim in tempor turpis nec euismod scelerisque quam turpis adipiscing lorem vitae mattis nibh ligula nec sem duis",
      "img": "https://picsum.photos/200/300?grayscale"
    },
    {
      "id": "0SG107J",
      "name": "Proboscidea louisianica (Mill.) Thell.",
      "des": "varius integer ac leo pellentesque ultrices mattis odio donec vitae nisi nam ultrices libero non mattis pulvinar nulla pede ullamcorper",
      "img": "https://picsum.photos/200/300?grayscale"
    },
    {
      "id": "049Y00Z",
      "name": "Meconella Nutt.",
      "des": "tristique in tempus sit amet sem fusce consequat nulla nisl nunc nisl duis bibendum felis sed interdum",
      "img": "https://picsum.photos/200/300?grayscale"
    },
    {
      "id": "0WUL47Z",
      "name": "Coreopsis floridana E.B. Sm.",
      "des": "ultrices erat tortor sollicitudin mi sit amet lobortis sapien sapien non mi integer ac neque duis bibendum morbi",
      "img": "https://picsum.photos/200/300?grayscale"
    },
    {
      "id": "06550ZZ",
      "name": "Quercus ×inconstans Palmer",
      "des": "id nisl venenatis lacinia aenean sit amet justo morbi ut odio",
      "img": "https://picsum.photos/200/300?grayscale"
    },
    {
      "id": "0SW70KZ",
      "name": "Dicranella hilariana (Mont.) Mitt.",
      "des": "nisi at nibh in hac habitasse platea dictumst aliquam augue quam sollicitudin vitae consectetuer",
      "img": "https://picsum.photos/200/300?grayscale"
    },
    {
      "id": "08CDXZZ",
      "name": "Lantana depressa Small",
      "des": "nonummy integer non velit donec diam neque vestibulum eget vulputate ut ultrices vel augue vestibulum ante ipsum primis in faucibus",
      "img": "https://picsum.photos/200/300?grayscale"
    },
    {
      "id": "0UW847Z",
      "name": "Jepsonia Small",
      "des": "ipsum dolor sit amet consectetuer adipiscing elit proin interdum mauris non ligula pellentesque",
      "img": "https://picsum.photos/200/300?grayscale"
    },
    {
      "id": "0XBF0ZZ",
      "name": "Athysanus pusillus (Hook.) Greene",
      "des": "eleifend luctus ultricies eu nibh quisque id justo sit amet sapien dignissim vestibulum vestibulum ante ipsum primis",
      "img": "https://picsum.photos/200/300?grayscale"
    },
    {
      "id": "03743D6",
      "name": "Uvularia perfoliata L.",
      "des": "tortor risus dapibus augue vel accumsan tellus nisi eu orci mauris lacinia sapien quis",
      "img": "https://picsum.photos/200/300?grayscale"
    },
    {
      "id": "037M066",
      "name": "Petractis Fr.",
      "des": "interdum eu tincidunt in leo maecenas pulvinar lobortis est phasellus sit amet erat nulla tempus",
      "img": "https://picsum.photos/200/300?grayscale"
    },
    {
      "id": "065Q3ZZ",
      "name": "Potentilla glandulosa Lindl. ssp. ashlandica (Greene) D.D. Keck",
      "des": "vel pede morbi porttitor lorem id ligula suspendisse ornare consequat lectus in est risus auctor sed tristique in tempus",
      "img": "https://picsum.photos/200/300?grayscale"
    },
    {
      "id": "05N80ZZ",
      "name": "Nemacladus rubescens Greene var. rubescens",
      "des": "laoreet ut rhoncus aliquet pulvinar sed nisl nunc rhoncus dui vel sem sed sagittis nam congue risus",
      "img": "https://picsum.photos/200/300?grayscale"
    },
    {
      "id": "0RSL35Z",
      "name": "Porophyllum scoparium A. Gray",
      "des": "consequat morbi a ipsum integer a nibh in quis justo",
      "img": "https://picsum.photos/200/300?grayscale"
    },
    {
      "id": "04UU3JZ",
      "name": "Arabis beckwithii S. Watson",
      "des": "faucibus orci luctus et ultrices posuere cubilia curae mauris viverra diam vitae",
      "img": "https://picsum.photos/200/300?grayscale"
    },
    {
      "id": "061809B",
      "name": "Houstonia wrightii A. Gray",
      "des": "nunc nisl duis bibendum felis sed interdum venenatis turpis enim blandit",
      "img": "https://picsum.photos/200/300?grayscale"
    },
    {
      "id": "0RU137Z",
      "name": "Alloteropsis cimicina (L.) Stapf",
      "des": "diam id ornare imperdiet sapien urna pretium nisl ut volutpat",
      "img": "https://picsum.photos/200/300?grayscale"
    },
    {
      "id": "037707Z",
      "name": "Amsonia hubrichtii Woodson",
      "des": "purus sit amet nulla quisque arcu libero rutrum ac lobortis vel dapibus at diam nam",
      "img": "https://picsum.photos/200/300?grayscale"
    },
    {
      "id": "061G07Y",
      "name": "Sorghum propinquum (Kunth) Hitchc.",
      "des": "ullamcorper purus sit amet nulla quisque arcu libero rutrum ac lobortis",
      "img": "https://picsum.photos/200/300?grayscale"
    },
    {
      "id": "0WP231Z",
      "name": "Hymenopappus scabiosaeus L'Hér.",
      "des": "ut suscipit a feugiat et eros vestibulum ac est lacinia nisi venenatis tristique fusce congue diam id ornare imperdiet",
      "img": "https://picsum.photos/200/300?grayscale"
    },
    {
      "id": "0QRC37Z",
      "name": "Penstemon ×dubius Davidson (pro sp.)",
      "des": "nascetur ridiculus mus etiam vel augue vestibulum rutrum rutrum neque aenean auctor gravida sem praesent id",
      "img": "https://picsum.photos/200/300?grayscale"
    },
    {
      "id": "04NU3ZZ",
      "name": "Buddleja racemosa Torr. ssp. incana (Torr.) Norm.",
      "des": "est et tempus semper est quam pharetra magna ac consequat metus sapien ut nunc vestibulum ante",
      "img": "https://picsum.photos/200/300?grayscale"
    },
    {
      "id": "0LXD4ZZ",
      "name": "Pipturus forbesii Krajina",
      "des": "mattis pulvinar nulla pede ullamcorper augue a suscipit nulla elit ac nulla sed vel enim sit amet nunc viverra",
      "img": "https://picsum.photos/200/300?grayscale"
    },
    {
      "id": "F0731YZ",
      "name": "Rinodina minutissima de Lesd.",
      "des": "pellentesque viverra pede ac diam cras pellentesque volutpat dui maecenas tristique est et tempus semper",
      "img": "https://picsum.photos/200/300?grayscale"
    },
    {
      "id": "0JR637Z",
      "name": "Cladonia phyllophora Hoffm.",
      "des": "at dolor quis odio consequat varius integer ac leo pellentesque ultrices mattis odio donec vitae nisi nam ultrices libero",
      "img": "https://picsum.photos/200/300?grayscale"
    },
    {
      "id": "D0002ZZ",
      "name": "Polygonum robustius (Small) Fernald",
      "des": "consequat varius integer ac leo pellentesque ultrices mattis odio donec vitae nisi nam ultrices libero non",
      "img": "https://picsum.photos/200/300?grayscale"
    },
    {
      "id": "04100KK",
      "name": "Calochortus nitidus Douglas",
      "des": "rhoncus dui vel sem sed sagittis nam congue risus semper porta volutpat quam pede",
      "img": "https://picsum.photos/200/300?grayscale"
    },
    {
      "id": "0FPB47Z",
      "name": "Setaria sphacelata (Schumach.) Stapf & C.E. Hubb. ex M.B. Moss var. splendida (Stapf) Clayton",
      "des": "sit amet eleifend pede libero quis orci nullam molestie nibh in lectus pellentesque at nulla suspendisse",
      "img": "https://picsum.photos/200/300?grayscale"
    },
    {
      "id": "059Q0ZZ",
      "name": "Potentilla concinna Richardson",
      "des": "sit amet sem fusce consequat nulla nisl nunc nisl duis bibendum",
      "img": "https://picsum.photos/200/300?grayscale"
    },
    {
      "id": "0WW0XYZ",
      "name": "Clermontia Gaudich.",
      "des": "fermentum donec ut mauris eget massa tempor convallis nulla neque libero convallis eget eleifend luctus",
      "img": "https://picsum.photos/200/300?grayscale"
    },
    {
      "id": "0HR6X74",
      "name": "Gonolobus Michx.",
      "des": "condimentum neque sapien placerat ante nulla justo aliquam quis turpis eget elit sodales scelerisque mauris",
      "img": "https://picsum.photos/200/300?grayscale"
    },
    {
      "id": "04VE3CZ",
      "name": "Eriophyllum lanatum (Pursh) Forbes var. aphanactis J.T. Howell",
      "des": "pede libero quis orci nullam molestie nibh in lectus pellentesque at nulla suspendisse potenti cras in purus eu",
      "img": "https://picsum.photos/200/300?grayscale"
    },
    {
      "id": "0994X0Z",
      "name": "Saussurea amara (L.) DC.",
      "des": "mauris lacinia sapien quis libero nullam sit amet turpis elementum ligula vehicula consequat",
      "img": "https://picsum.photos/200/300?grayscale"
    },
    {
      "id": "0D1907L",
      "name": "Prunus eremophila Prigge",
      "des": "etiam faucibus cursus urna ut tellus nulla ut erat id mauris vulputate elementum nullam varius nulla facilisi cras non velit",
      "img": "https://picsum.photos/200/300?grayscale"
    },
    {
      "id": "037P4DZ",
      "name": "Psilactis brevilingulata Sch. Bip. ex Hemsl.",
      "des": "ante ipsum primis in faucibus orci luctus et ultrices posuere cubilia curae duis",
      "img": "https://picsum.photos/200/300?grayscale"
    },
    {
      "id": "08QY0ZZ",
      "name": "Ramalina subleptocarpha Rundel & Bowler",
      "des": "nascetur ridiculus mus vivamus vestibulum sagittis sapien cum sociis natoque",
      "img": "https://picsum.photos/200/300?grayscale"
    },
    {
      "id": "0YUU47Z",
      "name": "Buellia stellulata (Taylor) Mudd",
      "des": "quam turpis adipiscing lorem vitae mattis nibh ligula nec sem duis aliquam",
      "img": "https://picsum.photos/200/300?grayscale"
    },
    {
      "id": "0TM74ZZ",
      "name": "Ruellia prostrata Poir.",
      "des": "in quam fringilla rhoncus mauris enim leo rhoncus sed vestibulum sit amet cursus id turpis integer aliquet massa",
      "img": "https://picsum.photos/200/300?grayscale"
    },
    {
      "id": "0PU707Z",
      "name": "Solidago sciaphila Steele",
      "des": "natoque penatibus et magnis dis parturient montes nascetur ridiculus mus etiam vel augue vestibulum rutrum rutrum neque aenean auctor",
      "img": "https://picsum.photos/200/300?grayscale"
    },
    {
      "id": "0W3F3ZZ",
      "name": "Rumex stenophyllus Ledeb.",
      "des": "pretium nisl ut volutpat sapien arcu sed augue aliquam erat volutpat in congue etiam justo",
      "img": "https://picsum.photos/200/300?grayscale"
    },
    {
      "id": "0W984ZX",
      "name": "Trachelospermum jasminoides (Lindl.) Lem.",
      "des": "justo eu massa donec dapibus duis at velit eu est congue elementum in hac habitasse platea dictumst morbi vestibulum velit",
      "img": "https://picsum.photos/200/300?grayscale"
    },
    {
      "id": "09QN8ZZ",
      "name": "Lessingia lemmonii A. Gray var. lemmonii",
      "des": "a odio in hac habitasse platea dictumst maecenas ut massa quis augue luctus tincidunt",
      "img": "https://picsum.photos/200/300?grayscale"
    },
    {
      "id": "B52LZZZ",
      "name": "Astragalus preussii A. Gray var. cutleri Barneby",
      "des": "metus aenean fermentum donec ut mauris eget massa tempor convallis nulla neque libero convallis eget eleifend luctus ultricies eu",
      "img": "https://picsum.photos/200/300?grayscale"
    },
    {
      "id": "B412110",
      "name": "Parmotrema hypotropum (Nyl.) Hale",
      "des": "donec dapibus duis at velit eu est congue elementum in hac habitasse platea",
      "img": "https://picsum.photos/200/300?grayscale"
    },
    {
      "id": "02WF0JZ",
      "name": "Symphyotrichum dumosum (L.) G.L. Nesom var. gracilipes (Wiegand) G.L. Nesom",
      "des": "pede ullamcorper augue a suscipit nulla elit ac nulla sed vel enim sit amet",
      "img": "https://picsum.photos/200/300?grayscale"
    },
    {
      "id": "0RGX34Z",
      "name": "Salvia sclarea L.",
      "des": "aliquam augue quam sollicitudin vitae consectetuer eget rutrum at lorem integer tincidunt ante vel ipsum praesent",
      "img": "https://picsum.photos/200/300?grayscale"
    },
    {
      "id": "0WW8XJZ",
      "name": "Harmonia stebbinsii (T.W. Nelson & J.P. Nelson) B.G. Baldw.",
      "des": "in tempus sit amet sem fusce consequat nulla nisl nunc nisl duis",
      "img": "https://picsum.photos/200/300?grayscale"
    },
    {
      "id": "04LM0ZZ",
      "name": "Carex microrhyncha Mack.",
      "des": "eget eros elementum pellentesque quisque porta volutpat erat quisque erat eros viverra eget congue eget semper rutrum nulla nunc purus",
      "img": "https://picsum.photos/200/300?grayscale"
    },
    {
      "id": "041C0JQ",
      "name": "Solenospora A. Massal.",
      "des": "morbi ut odio cras mi pede malesuada in imperdiet et commodo vulputate justo in blandit ultrices enim lorem ipsum",
      "img": "https://picsum.photos/200/300?grayscale"
    },
    {
      "id": "0JHN0VZ",
      "name": "Polychidium muscicola (Sw.) A. Gray",
      "des": "in lectus pellentesque at nulla suspendisse potenti cras in purus eu",
      "img": "https://picsum.photos/200/300?grayscale"
    },
    {
      "id": "072TXYZ",
      "name": "Henicodium (Müll. Hal.) Kindb.",
      "des": "curabitur convallis duis consequat dui nec nisi volutpat eleifend donec ut dolor morbi vel lectus in quam",
      "img": "https://picsum.photos/200/300?grayscale"
    },
    {
      "id": "09NM4ZZ",
      "name": "Galium serpenticum Dempster ssp. dayense Dempster & Ehrend.",
      "des": "ut ultrices vel augue vestibulum ante ipsum primis in faucibus orci luctus et ultrices posuere cubilia curae",
      "img": "https://picsum.photos/200/300?grayscale"
    },
    {
      "id": "04R34KZ",
      "name": "Linum subteres (Trel.) Winkl.",
      "des": "id turpis integer aliquet massa id lobortis convallis tortor risus dapibus augue vel accumsan tellus nisi eu orci mauris",
      "img": "https://picsum.photos/200/300?grayscale"
    },
    {
      "id": "0V2",
      "name": "Lecanora carpinea (L.) Vain.",
      "des": "nisl venenatis lacinia aenean sit amet justo morbi ut odio cras mi pede",
      "img": "https://picsum.photos/200/300?grayscale"
    },
    {
      "id": "06V13ZZ",
      "name": "Carex atrata L.",
      "des": "consequat metus sapien ut nunc vestibulum ante ipsum primis in faucibus",
      "img": "https://picsum.photos/200/300?grayscale"
    },
    {
      "id": "041J0AH",
      "name": "Delphinium novomexicanum Wooton",
      "des": "pulvinar nulla pede ullamcorper augue a suscipit nulla elit ac nulla sed vel enim sit",
      "img": "https://picsum.photos/200/300?grayscale"
    },
    {
      "id": "0U160J6",
      "name": "Ranunculus inamoenus Greene var. alpeophilus (A. Nelson) L.D. Benson",
      "des": "at turpis a pede posuere nonummy integer non velit donec",
      "img": "https://picsum.photos/200/300?grayscale"
    },
    {
      "id": "GZFZZZZ",
      "name": "Phyllanthus pentaphyllus C. Wright ex Griseb. ssp. pentaphyllus",
      "des": "nunc vestibulum ante ipsum primis in faucibus orci luctus et ultrices posuere cubilia curae mauris viverra diam vitae",
      "img": "https://picsum.photos/200/300?grayscale"
    },
    {
      "id": "04SH3ZZ",
      "name": "Keckiella rothrockii (A. Gray) Straw ssp. jacintensis (Abrams) Straw",
      "des": "pede ullamcorper augue a suscipit nulla elit ac nulla sed vel enim sit amet nunc viverra dapibus nulla suscipit ligula",
      "img": "https://picsum.photos/200/300?grayscale"
    },
    {
      "id": "021W48R",
      "name": "Begonia cucullata Willd.",
      "des": "amet lobortis sapien sapien non mi integer ac neque duis bibendum morbi non quam nec dui luctus rutrum",
      "img": "https://picsum.photos/200/300?grayscale"
    },
    {
      "id": "0RHV04Z",
      "name": "Aristida stricta Michx.",
      "des": "leo odio porttitor id consequat in consequat ut nulla sed accumsan felis ut",
      "img": "https://picsum.photos/200/300?grayscale"
    },
    {
      "id": "0P8Q4ZZ",
      "name": "Schoenoplectus torreyi (Olney) Palla",
      "des": "sit amet diam in magna bibendum imperdiet nullam orci pede venenatis non sodales sed tincidunt eu felis fusce posuere",
      "img": "https://picsum.photos/200/300?grayscale"
    },
    {
      "id": "0WBNXZZ",
      "name": "Lactuca serriola L.",
      "des": "maecenas ut massa quis augue luctus tincidunt nulla mollis molestie lorem quisque ut erat curabitur gravida nisi at",
      "img": "https://picsum.photos/200/300?grayscale"
    },
    {
      "id": "0W3M4ZZ",
      "name": "Lamium purpureum L.",
      "des": "ultrices posuere cubilia curae mauris viverra diam vitae quam suspendisse potenti nullam porttitor lacus",
      "img": "https://picsum.photos/200/300?grayscale"
    },
    {
      "id": "04V13DZ",
      "name": "Agastache pallida (Lindl.) Cory",
      "des": "non velit donec diam neque vestibulum eget vulputate ut ultrices vel augue vestibulum ante ipsum primis in faucibus orci",
      "img": "https://picsum.photos/200/300?grayscale"
    }
  ],
  "users": [
    {
      "id": "IDal-4NpZ",
      "name": "Vũ Thanh Hiếu",
      "phone": "0966187232",
      "email": "vuthanhhieu00@gmail.com",
      "password": "$2b$10$d34bvbemBJLhqdQ3cbKaR.TifPicXtBVGK7NcrKXhejqNaYg1X/yu",
      "isActive": true
    }
  ],
  "transactions": [
    {
      "id": "oQaqC8UUE",
      "userId": "oACesTOTJ",
      "bookId": "wCIYKqjWQ",
      "isComplete": false
    },
    {
      "id": "GrT6wa-ng",
      "userId": "uzy-vL4nS",
      "bookId": "wCIYKqjWQ",
      "isComplete": false
    },
    {
      "id": "4gAcLuB7I",
      "userId": "2Zk5YNvcV",
      "bookId": "h0NDa-xkJ",
      "isComplete": false
    }
  ]
}